[{"model": "census.edition", "pk": 1, "fields": {"title": 1, "Edition_number": "1", "Edition_format": "4\u00b0"}}, {"model": "census.edition", "pk": 2, "fields": {"title": 1, "Edition_number": "2", "Edition_format": "4\u00b0"}}, {"model": "census.edition", "pk": 3, "fields": {"title": 1, "Edition_number": "3", "Edition_format": "4\u00b0"}}, {"model": "census.edition", "pk": 4, "fields": {"title": 1, "Edition_number": "4", "Edition_format": "4\u00b0"}}, {"model": "census.edition", "pk": 5, "fields": {"title": 1, "Edition_number": "5", "Edition_format": "4\u00b0"}}, {"model": "census.edition", "pk": 6, "fields": {"title": 1, "Edition_number": "6", "Edition_format": "4\u00b0"}}, {"model": "census.edition", "pk": 7, "fields": {"title": 1, "Edition_number": "7", "Edition_format": "4\u00b0"}}, {"model": "census.edition", "pk": 8, "fields": {"title": 1, "Edition_number": "8", "Edition_format": "4\u00b0"}}, {"model": "census.edition", "pk": 9, "fields": {"title": 1, "Edition_number": "9", "Edition_format": "4\u00b0"}}, {"model": "census.edition", "pk": 10, "fields": {"title": 2, "Edition_number": "1", "Edition_format": "4\u00b0"}}, {"model": "census.edition", "pk": 11, "fields": {"title": 2, "Edition_number": "2", "Edition_format": "4\u00b0"}}, {"model": "census.edition", "pk": 12, "fields": {"title": 3, "Edition_number": "1", "Edition_format": "4\u00b0"}}, {"model": "census.edition", "pk": 13, "fields": {"title": 3, "Edition_number": "2", "Edition_format": "4\u00b0"}}, {"model": "census.edition", "pk": 14, "fields": {"title": 3, "Edition_number": "3", "Edition_format": "4\u00b0"}}, {"model": "census.edition", "pk": 15, "fields": {"title": 4, "Edition_number": "1", "Edition_format": "4\u00b0"}}, {"model": "census.edition", "pk": 16, "fields": {"title": 5, "Edition_number": "1", "Edition_format": "4\u00b0"}}, {"model": "census.edition", "pk": 17, "fields": {"title": 5, "Edition_number": "2", "Edition_format": "4\u00b0"}}, {"model": "census.edition", "pk": 18, "fields": {"title": 6, "Edition_number": "1", "Edition_format": "4\u00b0"}}, {"model": "census.edition", "pk": 19, "fields": {"title": 6, "Edition_number": "2", "Edition_format": "4\u00b0"}}, {"model": "census.edition", "pk": 20, "fields": {"title": 7, "Edition_number": "1", "Edition_format": "4\u00b0"}}, {"model": "census.edition", "pk": 21, "fields": {"title": 8, "Edition_number": "1", "Edition_format": "12\u00b0"}}, {"model": "census.edition", "pk": 22, "fields": {"title": 8, "Edition_number": "2", "Edition_format": "12\u00b0"}}, {"model": "census.edition", "pk": 23, "fields": {"title": 9, "Edition_number": "1", "Edition_format": "4\u00b0"}}, {"model": "census.edition", "pk": 24, "fields": {"title": 9, "Edition_number": "2", "Edition_format": "4\u00b0"}}, {"model": "census.edition", "pk": 25, "fields": {"title": 9, "Edition_number": "3", "Edition_format": "4\u00b0"}}, {"model": "census.edition", "pk": 26, "fields": {"title": 9, "Edition_number": "4", "Edition_format": "4\u00b0"}}, {"model": "census.edition", "pk": 27, "fields": {"title": 9, "Edition_number": "5", "Edition_format": "4\u00b0"}}, {"model": "census.edition", "pk": 28, "fields": {"title": 9, "Edition_number": "6", "Edition_format": "4\u00b0"}}, {"model": "census.edition", "pk": 29, "fields": {"title": 9, "Edition_number": "8", "Edition_format": "4\u00b0"}}, {"model": "census.edition", "pk": 30, "fields": {"title": 9, "Edition_number": "9", "Edition_format": "4\u00b0"}}, {"model": "census.edition", "pk": 31, "fields": {"title": 10, "Edition_number": "1", "Edition_format": "4\u00b0"}}, {"model": "census.edition", "pk": 32, "fields": {"title": 10, "Edition_number": "2", "Edition_format": "4\u00b0"}}, {"model": "census.edition", "pk": 33, "fields": {"title": 10, "Edition_number": "3", "Edition_format": "4\u00b0"}}, {"model": "census.edition", "pk": 34, "fields": {"title": 11, "Edition_number": "1", "Edition_format": "4\u00b0"}}, {"model": "census.edition", "pk": 35, "fields": {"title": 11, "Edition_number": "2", "Edition_format": "4\u00b0"}}, {"model": "census.edition", "pk": 36, "fields": {"title": 11, "Edition_number": "4", "Edition_format": "4\u00b0"}}, {"model": "census.edition", "pk": 37, "fields": {"title": 12, "Edition_number": "1", "Edition_format": "4\u00b0"}}, {"model": "census.edition", "pk": 38, "fields": {"title": 12, "Edition_number": "2", "Edition_format": "4\u00b0"}}, {"model": "census.edition", "pk": 39, "fields": {"title": 12, "Edition_number": "3", "Edition_format": "4\u00b0"}}, {"model": "census.edition", "pk": 40, "fields": {"title": 13, "Edition_number": "1", "Edition_format": "4\u00b0"}}, {"model": "census.edition", "pk": 41, "fields": {"title": 14, "Edition_number": "1", "Edition_format": "4\u00b0"}}, {"model": "census.edition", "pk": 42, "fields": {"title": 15, "Edition_number": "1", "Edition_format": "4\u00b0"}}, {"model": "census.edition", "pk": 43, "fields": {"title": 15, "Edition_number": "2", "Edition_format": "4\u00b0"}}, {"model": "census.edition", "pk": 44, "fields": {"title": 16, "Edition_number": "1", "Edition_format": "4\u00b0"}}, {"model": "census.edition", "pk": 45, "fields": {"title": 17, "Edition_number": "1", "Edition_format": "4\u00b0"}}, {"model": "census.edition", "pk": 46, "fields": {"title": 18, "Edition_number": "1", "Edition_format": "4\u00b0"}}, {"model": "census.edition", "pk": 47, "fields": {"title": 18, "Edition_number": "2", "Edition_format": "4\u00b0"}}, {"model": "census.edition", "pk": 48, "fields": {"title": 18, "Edition_number": "3", "Edition_format": "4\u00b0"}}, {"model": "census.edition", "pk": 49, "fields": {"title": 19, "Edition_number": "1", "Edition_format": "4\u00b0"}}, {"model": "census.edition", "pk": 50, "fields": {"title": 19, "Edition_number": "2", "Edition_format": "4\u00b0"}}, {"model": "census.edition", "pk": 51, "fields": {"title": 19, "Edition_number": "3", "Edition_format": "4\u00b0"}}, {"model": "census.edition", "pk": 52, "fields": {"title": 20, "Edition_number": "1", "Edition_format": "4\u00b0"}}, {"model": "census.edition", "pk": 53, "fields": {"title": 20, "Edition_number": "2", "Edition_format": "4\u00b0"}}, {"model": "census.edition", "pk": 54, "fields": {"title": 21, "Edition_number": "1", "Edition_format": "4\u00b0"}}, {"model": "census.edition", "pk": 55, "fields": {"title": 22, "Edition_number": "1", "Edition_format": "4\u00b0"}}, {"model": "census.edition", "pk": 56, "fields": {"title": 22, "Edition_number": "2", "Edition_format": "4\u00b0"}}, {"model": "census.edition", "pk": 57, "fields": {"title": 22, "Edition_number": "3", "Edition_format": "4\u00b0"}}, {"model": "census.edition", "pk": 58, "fields": {"title": 22, "Edition_number": "4", "Edition_format": "4\u00b0"}}, {"model": "census.edition", "pk": 59, "fields": {"title": 22, "Edition_number": "5", "Edition_format": "4\u00b0"}}, {"model": "census.edition", "pk": 60, "fields": {"title": 22, "Edition_number": "6", "Edition_format": "4\u00b0"}}, {"model": "census.edition", "pk": 61, "fields": {"title": 23, "Edition_number": "1", "Edition_format": "8\u00b0"}}, {"model": "census.edition", "pk": 62, "fields": {"title": 23, "Edition_number": "2", "Edition_format": "8\u00b0"}}, {"model": "census.edition", "pk": 63, "fields": {"title": 23, "Edition_number": "3", "Edition_format": "8\u00b0"}}, {"model": "census.edition", "pk": 64, "fields": {"title": 24, "Edition_number": "1", "Edition_format": "4\u00b0"}}, {"model": "census.edition", "pk": 65, "fields": {"title": 24, "Edition_number": "2", "Edition_format": "4\u00b0"}}, {"model": "census.edition", "pk": 66, "fields": {"title": 24, "Edition_number": "3", "Edition_format": "4\u00b0"}}, {"model": "census.edition", "pk": 67, "fields": {"title": 24, "Edition_number": "5", "Edition_format": "4\u00b0"}}, {"model": "census.edition", "pk": 68, "fields": {"title": 24, "Edition_number": "6", "Edition_format": "4\u00b0"}}, {"model": "census.edition", "pk": 69, "fields": {"title": 25, "Edition_number": "1", "Edition_format": "8\u00b0"}}, {"model": "census.edition", "pk": 70, "fields": {"title": 26, "Edition_number": "1", "Edition_format": "4\u00b0"}}, {"model": "census.edition", "pk": 71, "fields": {"title": 26, "Edition_number": "2", "Edition_format": "8\u00b0"}}, {"model": "census.edition", "pk": 72, "fields": {"title": 26, "Edition_number": "3", "Edition_format": "8\u00b0"}}, {"model": "census.edition", "pk": 73, "fields": {"title": 26, "Edition_number": "4", "Edition_format": "8\u00b0"}}, {"model": "census.edition", "pk": 74, "fields": {"title": 26, "Edition_number": "5", "Edition_format": "8\u00b0"}}, {"model": "census.edition", "pk": 75, "fields": {"title": 26, "Edition_number": "6", "Edition_format": "8\u00b0"}}, {"model": "census.edition", "pk": 76, "fields": {"title": 26, "Edition_number": "7", "Edition_format": "8\u00b0"}}, {"model": "census.edition", "pk": 77, "fields": {"title": 26, "Edition_number": "8", "Edition_format": "8\u00b0"}}, {"model": "census.edition", "pk": 78, "fields": {"title": 26, "Edition_number": "9", "Edition_format": "8\u00b0"}}, {"model": "census.edition", "pk": 79, "fields": {"title": 28, "Edition_number": "1", "Edition_format": "4\u00b0"}}, {"model": "census.edition", "pk": 80, "fields": {"title": 28, "Edition_number": "2", "Edition_format": "4\u00b0"}}, {"model": "census.edition", "pk": 81, "fields": {"title": 28, "Edition_number": "3", "Edition_format": "4\u00b0"}}, {"model": "census.edition", "pk": 82, "fields": {"title": 28, "Edition_number": "4", "Edition_format": "4\u00b0"}}, {"model": "census.edition", "pk": 83, "fields": {"title": 28, "Edition_number": "5", "Edition_format": "4\u00b0"}}, {"model": "census.edition", "pk": 84, "fields": {"title": 28, "Edition_number": "6", "Edition_format": "4\u00b0"}}, {"model": "census.edition", "pk": 85, "fields": {"title": 29, "Edition_number": "1", "Edition_format": "4\u00b0"}}, {"model": "census.edition", "pk": 86, "fields": {"title": 29, "Edition_number": "2", "Edition_format": "4\u00b0"}}, {"model": "census.edition", "pk": 87, "fields": {"title": 29, "Edition_number": "3", "Edition_format": "4\u00b0"}}, {"model": "census.edition", "pk": 88, "fields": {"title": 29, "Edition_number": "4", "Edition_format": "4\u00b0"}}, {"model": "census.edition", "pk": 89, "fields": {"title": 29, "Edition_number": "5", "Edition_format": "4\u00b0"}}, {"model": "census.edition", "pk": 90, "fields": {"title": 29, "Edition_number": "6", "Edition_format": "4\u00b0"}}, {"model": "census.edition", "pk": 91, "fields": {"title": 29, "Edition_number": "7", "Edition_format": "4\u00b0"}}, {"model": "census.edition", "pk": 92, "fields": {"title": 29, "Edition_number": "8", "Edition_format": "4\u00b0"}}, {"model": "census.edition", "pk": 93, "fields": {"title": 30, "Edition_number": "1", "Edition_format": "4\u00b0"}}, {"model": "census.edition", "pk": 94, "fields": {"title": 30, "Edition_number": "2", "Edition_format": "4\u00b0"}}, {"model": "census.edition", "pk": 95, "fields": {"title": 30, "Edition_number": "3", "Edition_format": "4\u00b0"}}, {"model": "census.edition", "pk": 96, "fields": {"title": 30, "Edition_number": "4", "Edition_format": "4\u00b0"}}, {"model": "census.edition", "pk": 97, "fields": {"title": 30, "Edition_number": "5", "Edition_format": "4\u00b0"}}, {"model": "census.edition", "pk": 98, "fields": {"title": 31, "Edition_number": "1", "Edition_format": "4\u00b0"}}, {"model": "census.edition", "pk": 99, "fields": {"title": 32, "Edition_number": "1", "Edition_format": "4\u00b0"}}, {"model": "census.edition", "pk": 100, "fields": {"title": 32, "Edition_number": "2", "Edition_format": "4\u00b0"}}, {"model": "census.edition", "pk": 101, "fields": {"title": 32, "Edition_number": "3", "Edition_format": "4\u00b0"}}, {"model": "census.edition", "pk": 102, "fields": {"title": 32, "Edition_number": "4", "Edition_format": "4\u00b0"}}, {"model": "census.edition", "pk": 103, "fields": {"title": 33, "Edition_number": "1", "Edition_format": "4\u00b0"}}, {"model": "census.edition", "pk": 104, "fields": {"title": 34, "Edition_number": "1", "Edition_format": "4\u00b0"}}, {"model": "census.edition", "pk": 105, "fields": {"title": 34, "Edition_number": "2", "Edition_format": "4\u00b0"}}, {"model": "census.edition", "pk": 106, "fields": {"title": 35, "Edition_number": "1", "Edition_format": "4\u00b0"}}, {"model": "census.edition", "pk": 107, "fields": {"title": 35, "Edition_number": "2", "Edition_format": "4\u00b0"}}, {"model": "census.edition", "pk": 108, "fields": {"title": 35, "Edition_number": "3", "Edition_format": "4\u00b0"}}, {"model": "census.edition", "pk": 109, "fields": {"title": 36, "Edition_number": "1", "Edition_format": "4\u00b0"}}, {"model": "census.edition", "pk": 110, "fields": {"title": 37, "Edition_number": "1", "Edition_format": "4\u00b0"}}, {"model": "census.edition", "pk": 111, "fields": {"title": 38, "Edition_number": "1", "Edition_format": "4\u00b0"}}, {"model": "census.edition", "pk": 112, "fields": {"title": 38, "Edition_number": "2", "Edition_format": "4\u00b0"}}, {"model": "census.edition", "pk": 113, "fields": {"title": 38, "Edition_number": "3", "Edition_format": "8\u00b0"}}, {"model": "census.edition", "pk": 114, "fields": {"title": 38, "Edition_number": "4", "Edition_format": "8\u00b0"}}, {"model": "census.edition", "pk": 115, "fields": {"title": 38, "Edition_number": "5", "Edition_format": "8\u00b0"}}, {"model": "census.edition", "pk": 116, "fields": {"title": 38, "Edition_number": "6", "Edition_format": "8\u00b0"}}, {"model": "census.edition", "pk": 117, "fields": {"title": 38, "Edition_number": "7", "Edition_format": "8\u00b0"}}, {"model": "census.edition", "pk": 118, "fields": {"title": 38, "Edition_number": "8", "Edition_format": "8\u00b0"}}, {"model": "census.edition", "pk": 119, "fields": {"title": 38, "Edition_number": "9", "Edition_format": "8\u00b0"}}, {"model": "census.edition", "pk": 120, "fields": {"title": 38, "Edition_number": "10", "Edition_format": "8\u00b0"}}, {"model": "census.edition", "pk": 121, "fields": {"title": 38, "Edition_number": "11", "Edition_format": "8\u00b0"}}, {"model": "census.edition", "pk": 122, "fields": {"title": 38, "Edition_number": "12", "Edition_format": "8\u00b0"}}, {"model": "census.edition", "pk": 123, "fields": {"title": 38, "Edition_number": "13", "Edition_format": "8\u00b0"}}, {"model": "census.edition", "pk": 124, "fields": {"title": 38, "Edition_number": "14", "Edition_format": "8\u00b0"}}, {"model": "census.edition", "pk": 125, "fields": {"title": 38, "Edition_number": "15", "Edition_format": "8\u00b0"}}, {"model": "census.edition", "pk": 126, "fields": {"title": 38, "Edition_number": "16", "Edition_format": "16\u00b0"}}, {"model": "census.edition", "pk": 127, "fields": {"title": 38, "Edition_number": "17", "Edition_format": "16\u00b0"}}, {"model": "census.edition", "pk": 128, "fields": {"title": 39, "Edition_number": "1", "Edition_format": "4\u00b0"}}, {"model": "census.edition", "pk": 129, "fields": {"title": 40, "Edition_number": "1", "Edition_format": "4\u00b0"}}, {"model": "census.edition", "pk": 130, "fields": {"title": 40, "Edition_number": "2", "Edition_format": "4\u00b0"}}, {"model": "census.edition", "pk": 131, "fields": {"title": 11, "Edition_number": "3", "Edition_format": "4\u00b0"}}, {"model": "census.edition", "pk": 132, "fields": {"title": 11, "Edition_number": "5", "Edition_format": "4\u00b0"}}, {"model": "census.edition", "pk": 133, "fields": {"title": 24, "Edition_number": "4", "Edition_format": "4\u00b0"}}, {"model": "census.edition", "pk": 134, "fields": {"title": 9, "Edition_number": "7", "Edition_format": "4\u00b0"}}]